odoo/addons/l10n_th_withholding_tax_report/README.rst
odoo/addons/l10n_th_withholding_tax_report/__init__.py
odoo/addons/l10n_th_withholding_tax_report/__manifest__.py
odoo/addons/l10n_th_withholding_tax_report/data/paper_format.xml
odoo/addons/l10n_th_withholding_tax_report/data/report_data.xml
odoo/addons/l10n_th_withholding_tax_report/i18n/l10n_th_withholding_tax_report.pot
odoo/addons/l10n_th_withholding_tax_report/readme/CONTRIBUTORS.rst
odoo/addons/l10n_th_withholding_tax_report/readme/DESCRIPTION.rst
odoo/addons/l10n_th_withholding_tax_report/readme/HISTORY.rst
odoo/addons/l10n_th_withholding_tax_report/readme/USAGE.rst
odoo/addons/l10n_th_withholding_tax_report/report/__init__.py
odoo/addons/l10n_th_withholding_tax_report/report/report_withholding_tax.py
odoo/addons/l10n_th_withholding_tax_report/report/report_withholding_tax_xlsx.py
odoo/addons/l10n_th_withholding_tax_report/report/templates/layouts.xml
odoo/addons/l10n_th_withholding_tax_report/report/templates/report_template.xml
odoo/addons/l10n_th_withholding_tax_report/report/templates/report_withholding_tax_pdf.xml
odoo/addons/l10n_th_withholding_tax_report/report_txt/report.xml
odoo/addons/l10n_th_withholding_tax_report/report_txt/report_withholding_tax_txt.xlsx
odoo/addons/l10n_th_withholding_tax_report/report_txt/templates.xml
odoo/addons/l10n_th_withholding_tax_report/static/description/icon.png
odoo/addons/l10n_th_withholding_tax_report/static/description/index.html
odoo/addons/l10n_th_withholding_tax_report/static/src/css/report.css
odoo/addons/l10n_th_withholding_tax_report/static/src/js/withholding_tax_report_backend.js
odoo/addons/l10n_th_withholding_tax_report/static/src/js/withholding_tax_report_widgets.js
odoo/addons/l10n_th_withholding_tax_report/wizard/__init__.py
odoo/addons/l10n_th_withholding_tax_report/wizard/withholding_tax_report_wizard.py
odoo/addons/l10n_th_withholding_tax_report/wizard/withholding_tax_report_wizard_view.xml
odoo12_addon_l10n_th_withholding_tax_report-12.0.1.0.3.dist-info/METADATA
odoo12_addon_l10n_th_withholding_tax_report-12.0.1.0.3.dist-info/WHEEL
odoo12_addon_l10n_th_withholding_tax_report-12.0.1.0.3.dist-info/top_level.txt
odoo12_addon_l10n_th_withholding_tax_report-12.0.1.0.3.dist-info/RECORD
